{"artwork":null,"bars":20,"bpm":130,"collaborative":false,"color":"#f067d1","created":"2024-10-11 02:01:53.299000","deleted":false,"description":"","gadget-details":[{"beats":16,"color":"#2f9aef","created":"2024-11-07 02:13:36.737000","deleted":false,"description":"","id":695717,"idata":{"author":"Anonymous","cloned":false,"displayOrder":1,"editor-theme":"tunepad-dark","gain":1,"hasError":false,"midi-input":false,"midi-output":false,"minimized":false,"pan":0,"patchId":223,"python":"# New TunePad cell\nplayNote(72, beats = 1, velocity = 100)\nplayNote(60, beats = 1, velocity = 100)\nplayNote(69, beats = 1, velocity = 100)\nplayNote(60, beats = 1, velocity = 100)\nplayNote(72, beats = 1, velocity = 100)\nplayNote(62, beats = 1, velocity = 100)\nplayNote(60, beats = 1, velocity = 100)\nplayNote(62, beats = 1, velocity = 100)\n\nplayNote(72, beats = 1, velocity = 100)\nplayNote(60, beats = 1, velocity = 100)\nplayNote(69, beats = 1, velocity = 100)\nplayNote(60, beats = 1, velocity = 100)\nplayNote(72, beats = 1, velocity = 100)\nplayNote(62, beats = 1, velocity = 100)\nplayNote(60, beats = 1, velocity = 100)\nplayNote(62, beats = 1, velocity = 100)\n\n\n\n\n","show-editor":true,"show-instrument":true,"show-notation":true,"show-output":false,"show-timeline":true},"instrument":"piano","modified":"2024-11-08 01:16:56.859000","name":"MELODY - SYNTH LEAD","public":false,"remix_parent":null,"version":"2.0","voice":"Soft Synth"},{"beats":72,"color":"#2f9aef","created":"2024-11-07 04:34:00.384000","deleted":false,"description":"","id":695732,"idata":{"author":"Anonymous","cloned":false,"displayOrder":2,"editor-theme":"tunepad-dark","gain":1,"hasError":false,"midi-input":false,"midi-output":false,"minimized":false,"pan":0,"patchId":84,"python":"# New TunePad cell\n\n# define synth bassline function with initial rest\ndef play_synth_bassline():\n    playNote(21, beats = 1)\n    playNote(21, beats = 0.5)\n    playNote(19, beats = 0.5)\n    playNote(17, beats = 1)\n    playNote(21, beats = 0.5)\n    playNote(19, beats = 0.5)\n    \n# intial rest before starting the loop\nrest(8)\n\n    \n# Loop the bassline to play continuously or set amount of time\nfor _ in range(16): #adjust how many times it loops\n    play_synth_bassline()\n    \n    \n    \n\n\n\n\n\n\n\n\n\n\n","show-editor":true,"show-instrument":true,"show-notation":true,"show-output":false,"show-timeline":true},"instrument":"bass","modified":"2024-11-07 07:43:41.554000","name":"BASSLINE - SYNTH BASE","public":false,"remix_parent":null,"version":"2.0","voice":"Synth Pop Bass"},{"beats":216,"color":"#2f9aef","created":"2024-11-07 04:35:24.447000","deleted":false,"description":"","id":695738,"idata":{"author":"Anonymous","cloned":false,"displayOrder":3,"editor-theme":"tunepad-dark","gain":1,"hasError":false,"midi-input":false,"midi-output":false,"minimized":false,"pan":0,"patchId":254,"python":"# New TunePad cell\n# CHORDS – SYNTH PAD\ndef play_chords():\n    rest(16)  # Rest for the first 16 beats\n    beats_played = 16\n    while beats_played < 320 - 8:  # Play until the final 8-beat rest\n        for _ in range(2):  # Each loop iteration plays for 32 beats\n            playNote([42, 46, 49], beats=4, velocity=60)\n            playNote([44, 48, 51], beats=4, velocity=60)\n            playNote([46, 49, 53], beats=4, velocity=60)\n            playNote([44, 48, 53], beats=4, velocity=60)\n            beats_played += 32\n        rest(16)  # 16-beat break\n        beats_played += 16\n    rest(8)  # Final 8-beat rest before the end\n\n# Call the chords function\nplay_chords()\n\n\n    \n    \n    \n    \n    \n    \n    \n\n\n\n","show-editor":true,"show-instrument":true,"show-notation":true,"show-output":false,"show-timeline":true},"instrument":"piano","modified":"2024-11-07 07:57:43.473000","name":" CHORDS - SYNTH PAD","public":false,"remix_parent":null,"version":"2.0","voice":"Searing Lead"},{"beats":92,"color":"#2f9aef","created":"2024-11-07 04:36:04.325000","deleted":false,"description":"","id":695739,"idata":{"author":"Anonymous","cloned":false,"displayOrder":4,"editor-theme":"tunepad-dark","gain":1,"hasError":false,"midi-input":false,"midi-output":false,"minimized":false,"pan":0,"patchId":466,"python":"# New TunePad cell\n\nkick = 1\nsnare = 3\n\n# DRUMS – ELECTRIC DRUMS\ndef play_electric_drums():\n    beats_played = 0\n    while beats_played < 320:\n        if 160 <= beats_played < 176:  # Middle 16-beat rest section\n            rest(16)\n            beats_played += 16\n        else:\n            playNote(kick, beats=1, velocity=80)\n            playNote(snare, beats=0.5, velocity=80)\n            playNote(kick, beats=0.5, velocity=100)\n            playNote(kick, beats=1, velocity=80)\n            playNote(snare, beats=1, velocity=100)\n            beats_played += 16  # Add the total beats played in each iteration\n\n# Call the electric drums function\nplay_electric_drums()\n\n    ","show-editor":true,"show-instrument":true,"show-notation":true,"show-output":false,"show-timeline":true},"instrument":"drums","modified":"2024-11-07 07:47:42.492000","name":"DRUMS - ELECTRONIC DRUMS","public":false,"remix_parent":null,"version":"2.0","voice":"909 Drumkit"},{"beats":232,"color":"#2f9aef","created":"2024-11-07 06:02:11.250000","deleted":false,"description":"","id":695745,"idata":{"author":"Anonymous","cloned":false,"displayOrder":5,"editor-theme":"tunepad-dark","gain":1,"hasError":false,"midi-input":false,"midi-output":false,"minimized":false,"pan":0,"patchId":466,"python":"# New TunePad cell\n# DRUMS – HIHAT / TOM\ndef play_hihat_tom():\n    rest(16)  # Initial rest for the first 16 beats\n    beats_played = 16\n    \n    while beats_played < 320 - 8:  # Play until the final 8-beat rest\n        # Play for 16 beats\n        for _ in range(2):  # Each loop iteration plays for 8 beats; repeat twice for 16 beats total\n            playNote(8, beats=0.5, velocity=80)\n            playNote(5, beats=0.5, velocity=80)\n            playNote(8, beats=0.5, velocity=80)\n            playNote(5, beats=0.5, velocity=80)\n            playNote(8, beats=0.5, velocity=80)\n            playNote(5, beats=0.5, velocity=80)\n            playNote(8, beats=0.5, velocity=80)\n            playNote(5, beats=0.5, velocity=80)\n        \n        beats_played += 16  # Track the beats played\n\n        # 8-beat rest between each 16-beat section\n        rest(8)\n        beats_played += 8\n    \n    rest(8)  # Final 8-beat rest before the end\n\n# Call the hihat/tom function\nplay_hihat_tom()\n\n\n\n    \n\n\n\n\n\n\n\n\n\n\n\n\n","show-editor":true,"show-instrument":true,"show-notation":true,"show-output":false,"show-timeline":true},"instrument":"drums","modified":"2024-11-07 07:55:34.311000","name":"DRUMS - ELECTRONIC DRUMS PEAK","public":false,"remix_parent":null,"version":"2.0","voice":"909 Drumkit"}],"id":89266,"import_export_version":1,"meter":"4/4","modified":"2024-11-08 01:17:14.278000","name":"A2 Project - Song","preview":null,"pucks":{"daw-zoom-factor":0.5,"key":"C major","owner_id":"b9ddf5bf-0c09-4d00-9362-add1fe42575b"},"remix_parent":null,"summary":"","tags":[],"tracks":[{"clips":[{"beats":16,"color":"blue","end":80,"start":0,"trim":0,"waveform":false}],"color":"blue","gadget_id":695717,"gain":0,"hidden":false,"id":695717,"mute":false,"name":"MELODY - SYNTH LEAD","order":0,"pan":0,"solo":false,"solo-mute":false},{"clips":[{"beats":72,"color":"magenta","end":80,"start":0,"trim":0,"waveform":false}],"color":"magenta","gadget_id":695732,"gain":0,"hidden":false,"id":695732,"mute":false,"name":"BASSLINE - SYNTH BASE","order":1,"pan":0,"solo":false,"solo-mute":false},{"clips":[{"beats":216,"color":"blue","end":80,"start":0,"trim":0,"waveform":false}],"color":"blue","gadget_id":695738,"gain":0,"hidden":false,"id":695738,"mute":false,"name":" CHORDS - SYNTH PAD","order":2,"pan":0,"solo":false,"solo-mute":false},{"clips":[{"beats":92,"color":"green","end":80,"start":0,"trim":0,"waveform":false}],"color":"green","gadget_id":695739,"gain":0,"hidden":false,"id":695739,"mute":false,"name":"DRUMS - ELECTRONIC DRUMS","order":3,"pan":0,"solo":false,"solo-mute":false},{"clips":[{"beats":232,"color":"green","end":80,"start":0,"trim":0,"waveform":false}],"color":"green","gadget_id":695745,"gain":0,"hidden":false,"id":695745,"mute":false,"name":"DRUMS - ELECTRONIC DRUMS PEAK","order":4,"pan":0,"solo":false,"solo-mute":false}],"user_id":"b9ddf5bf-0c09-4d00-9362-add1fe42575b","username":"finnd13","visibility":"private"}